llmterface/__init__.py
llmterface/exceptions.py
llmterface/helpers.py
llmterface/llmterface.py
llmterface/models/config_base.py
llmterface/models/generic_chat.py
llmterface/models/generic_config.py
llmterface/models/generic_model_types.py
llmterface/models/generic_response.py
llmterface/models/question.py
llmterface/models/simple_answers.py
llmterface/providers/__init__.py
llmterface/providers/discovery.py
llmterface/providers/provider_chat.py
llmterface/providers/provider_config.py
llmterface/providers/provider_spec.py
llmterface-0.1.0.dist-info/METADATA
llmterface-0.1.0.dist-info/WHEEL
llmterface-0.1.0.dist-info/licenses/LICENSE
llmterface-0.1.0.dist-info/RECORD
