Metadata-Version: 2.4
Name: llmterface
Version: 0.1.0
Summary: Intentionally Simple. Generic LLM interface
Author-email: "D. Zachary Wheeler" <celestialswashbuckler@gmail.com>
License-Expression: MIT
License-File: LICENSE
Keywords: ai,chat,interface,llm,plugin,provider
Classifier: Development Status :: 3 - Alpha
Classifier: Framework :: Pydantic :: 2
Classifier: Intended Audience :: Developers
Classifier: License :: OSI Approved :: MIT License
Classifier: Natural Language :: English
Classifier: Operating System :: OS Independent
Classifier: Programming Language :: Python :: 3
Classifier: Programming Language :: Python :: 3.11
Classifier: Programming Language :: Python :: 3.12
Classifier: Programming Language :: Python :: 3.13
Classifier: Topic :: Scientific/Engineering :: Artificial Intelligence
Classifier: Topic :: Software Development :: Libraries
Classifier: Topic :: Utilities
Requires-Python: <4.0,>=3.11
Requires-Dist: pydantic<3.0.0,>=2.12.5
Provides-Extra: all
Requires-Dist: llmterface-gemini<1.0.0,>=0.1.0; extra == 'all'
Provides-Extra: gemini
Requires-Dist: llmterface-gemini<1.0.0,>=0.1.0; extra == 'gemini'
